[
  {
    "name": "Celts",
    "buildings": [
      {
        "name": "Archery Range",
        "units": {
          "archer": true,
          "crossbowman": true,
          "arbalest": false,
          "skirmisher": true,
          "elite_skirmisher": true,
          "cavalry_archer": true,
          "heavy_cavalry_archer": true,
          "hand_cannoneer": false
        },
        "technologies": {
          "thumb_ring": false,
          "parthian_tactics": false
        }
      }
    ]
  },
  {
    "name": "Persians",
    "buildings": [
      {
        "name": "Archery Range",
        "units": {
          "archer": true,
          "crossbowman": true,
          "arbalest": false,
          "skirmisher": true,
          "elite_skirmisher": true,
          "cavalry_archer": true,
          "heavy_cavalry_archer": true,
          "hand_cannoneer": true
        },
        "technologies": {
          "thumb_ring": true,
          "parthian_tactics": true
        }
      }
    ]
  }
]